project_Potato_Man/test1.py
project_Potato_Man/test2.py
project_Potato_Man-0.0.0.1.dist-info/METADATA
project_Potato_Man-0.0.0.1.dist-info/WHEEL
project_Potato_Man-0.0.0.1.dist-info/top_level.txt
project_Potato_Man-0.0.0.1.dist-info/RECORD
