Metadata-Version: 2.1
Name: project-Potato-Man
Version: 0.0.0.1
Summary: My_First_project_start
Home-page: https://github.com/hunterhhunter
Author: Justin jin
Author-email: slugger613@naver.com
License: MIT
Platform: UNKNOWN
Requires-Python: >=3
